arsenic_tools/__init__.py
arsenic_tools-0.1.0.dist-info/METADATA
arsenic_tools-0.1.0.dist-info/WHEEL
arsenic_tools-0.1.0.dist-info/RECORD
