Metadata-Version: 2.4
Name: arsenic-tools
Version: 0.1.0
Summary: A utility package for demonstration.
Author-email: Arsenic Developer <your_email@example.com>
Requires-Python: >=3.8
